pydal2sql/__about__.py
pydal2sql/__init__.py
pydal2sql/cli.py
pydal2sql/py.typed
pydal2sql/typer_support.py
pydal2sql/types.py
pydal2sql-1.3.1.dist-info/METADATA
pydal2sql-1.3.1.dist-info/WHEEL
pydal2sql-1.3.1.dist-info/entry_points.txt
pydal2sql-1.3.1.dist-info/licenses/LICENSE.txt
pydal2sql-1.3.1.dist-info/RECORD
