Metadata-Version: 2.4
Name: pydal2sql
Version: 1.3.1
Summary: Convert pydal define_tables to SQL using pydal's CREATE TABLE logic.
Project-URL: Documentation, https://github.com/robinvandernoord/pydal2sql#readme
Project-URL: Issues, https://github.com/robinvandernoord/pydal2sql/issues
Project-URL: Source, https://github.com/robinvandernoord/pydal2sql
Author-email: Robin van der Noord <robinvandernoord@gmail.com>
License-Expression: MIT
License-File: LICENSE.txt
Keywords: databases,pydal,sql
Classifier: Development Status :: 4 - Beta
Classifier: Programming Language :: Python
Classifier: Programming Language :: Python :: 3.10
Classifier: Programming Language :: Python :: 3.11
Classifier: Programming Language :: Python :: 3.12
Classifier: Programming Language :: Python :: 3.13
Classifier: Programming Language :: Python :: 3.14
Classifier: Programming Language :: Python :: Implementation :: CPython
Classifier: Programming Language :: Python :: Implementation :: PyPy
Requires-Python: >=3.10
Requires-Dist: configuraptor>=1.23
Requires-Dist: gitpython
Requires-Dist: pydal
Requires-Dist: pydal2sql-core>=0.5.0
Requires-Dist: rich
Requires-Dist: su6>=1.10.0
Requires-Dist: typer
Provides-Extra: all
Requires-Dist: pydal2sql-core[all]; extra == 'all'
Provides-Extra: dev
Requires-Dist: contextlib-chdir; extra == 'dev'
Requires-Dist: hatch; extra == 'dev'
Requires-Dist: psycopg2-binary; extra == 'dev'
Requires-Dist: pymysql; extra == 'dev'
Requires-Dist: python-semantic-release<8; extra == 'dev'
Requires-Dist: su6[all]; extra == 'dev'
Provides-Extra: mysql
Requires-Dist: pymysql; extra == 'mysql'
Provides-Extra: psql
Requires-Dist: psycopg2-binary; extra == 'psql'
